{
  "songName": "Californiacation ",
  "lyrics": [
    {
      "text": "Intro & verse: x2",
      "type": "words"
    },
    {
      "text": "Am                   F",
      "type": "chords"
    },
    {
      "text": "Am                   F",
      "type": "chords"
    },
    {
      "text": "Am",
      "type": "chords"
    },
    {
      "text": "Psychic spies from China",
      "type": "words"
    },
    {
      "text": "F",
      "type": "chords"
    },
    {
      "text": "Try to steal your mind’s elation",
      "type": "words"
    },
    {
      "text": "Am",
      "type": "chords"
    },
    {
      "text": "a Little girls from Sweden",
      "type": "words"
    },
    {
      "text": "F",
      "type": "chords"
    },
    {
      "text": "Dream of silver screen quotations",
      "type": "words"
    },
    {
      "text": "C                 G",
      "type": "chords"
    },
    {
      "text": "And if you want these kind of dreams",
      "type": "words"
    },
    {
      "text": "F        Dm     Am",
      "type": "chords"
    },
    {
      "text": "It’s Californication",
      "type": "words"
    },
    {
      "text": "Repeat intro",
      "type": "words"
    },
    {
      "text": "Am",
      "type": "chords"
    },
    {
      "text": "It’s the edge of the world",
      "type": "words"
    },
    {
      "text": "F",
      "type": "chords"
    },
    {
      "text": "And all of western civilization",
      "type": "words"
    },
    {
      "text": "Am",
      "type": "chords"
    },
    {
      "text": "The sun may rise in the East",
      "type": "words"
    },
    {
      "text": "F",
      "type": "chords"
    },
    {
      "text": "At least it settles in the final location",
      "type": "words"
    },
    {
      "text": "C               G",
      "type": "chords"
    },
    {
      "text": "It’s understood that Hollywood",
      "type": "words"
    },
    {
      "text": "F        Dm     Am F Am F",
      "type": "chords"
    },
    {
      "text": "sells Californication",
      "type": "words"
    },
    {
      "text": "Chorus:",
      "type": "words"
    },
    {
      "text": "Am",
      "type": "chords"
    },
    {
      "text": "Pay your surgeon very well",
      "type": "words"
    },
    {
      "text": "F",
      "type": "chords"
    },
    {
      "text": "To break the spell of aging",
      "type": "words"
    },
    {
      "text": "Am",
      "type": "chords"
    },
    {
      "text": "Celebrity skin is this your chin",
      "type": "words"
    },
    {
      "text": "F                       Am",
      "type": "chords"
    },
    {
      "text": "Or is that war your waging",
      "type": "words"
    },
    {
      "text": "Am            F   Am               F",
      "type": "chords"
    },
    {
      "text": "First born unicorn  Hard core soft porn",
      "type": "words"
    },
    {
      "text": "C           G    Dm    Am  C           G    Dm",
      "type": "chords"
    },
    {
      "text": "Dream of Californication   Dream of Californication",
      "type": "words"
    },
    {
      "text": "Bridge (with intro...):",
      "type": "words"
    },
    {
      "text": "Am        F         Am          F",
      "type": "chords"
    },
    {
      "text": "Am",
      "type": "chords"
    },
    {
      "text": "Marry me girl be my fairy to the world",
      "type": "words"
    },
    {
      "text": "F",
      "type": "chords"
    },
    {
      "text": "Be my very own constellation",
      "type": "words"
    },
    {
      "text": "Am",
      "type": "chords"
    },
    {
      "text": "A teenage bride with a baby inside",
      "type": "words"
    },
    {
      "text": "F",
      "type": "chords"
    },
    {
      "text": "Getting high on information",
      "type": "words"
    },
    {
      "text": "C                    G",
      "type": "chords"
    },
    {
      "text": "And buy me a star on the boulevard",
      "type": "words"
    },
    {
      "text": "F        Dm     Am F Am F",
      "type": "chords"
    },
    {
      "text": "It’s Californication",
      "type": "words"
    },
    {
      "text": "Am",
      "type": "chords"
    },
    {
      "text": "Space may be the final frontier",
      "type": "words"
    },
    {
      "text": "F",
      "type": "chords"
    },
    {
      "text": "But it’s made in a Hollywood basement",
      "type": "words"
    },
    {
      "text": "Am",
      "type": "chords"
    },
    {
      "text": "Cobain can you hear the spheres",
      "type": "words"
    },
    {
      "text": "F",
      "type": "chords"
    },
    {
      "text": "Singing songs off station to station",
      "type": "words"
    },
    {
      "text": "C             G",
      "type": "chords"
    },
    {
      "text": "And Alderon’s not far away",
      "type": "words"
    },
    {
      "text": "F        Dm     Am F Am F",
      "type": "chords"
    },
    {
      "text": "It’s Californication",
      "type": "words"
    },
    {
      "text": "Am                                      F",
      "type": "chords"
    },
    {
      "text": "Born and raised by those who praise Control of population",
      "type": "words"
    },
    {
      "text": "Am                             F",
      "type": "chords"
    },
    {
      "text": "everybody’s been there  and  I don’t mean on vacation",
      "type": "words"
    },
    {
      "text": "Am            F   Am               F",
      "type": "chords"
    },
    {
      "text": "First born unicorn  Hard core soft porn",
      "type": "words"
    },
    {
      "text": "C           G    Dm    Am  C           G    Dm",
      "type": "chords"
    },
    {
      "text": "Dream of Californication   Dream of Californication",
      "type": "words"
    },
    {
      "text": "Solo:",
      "type": "words"
    },
    {
      "text": "F#m           D       F#m          D",
      "type": "chords"
    },
    {
      "text": "Bm         D        A          E",
      "type": "chords"
    },
    {
      "text": "F#m       D    F#m            D",
      "type": "chords"
    },
    {
      "text": "Bm     D      A     E       Bm",
      "type": "chords"
    },
    {
      "text": "D      A        E         Bm",
      "type": "chords"
    },
    {
      "text": "D       A      E          Am",
      "type": "chords"
    },
    {
      "text": "Am",
      "type": "chords"
    },
    {
      "text": "Destruction leads to a very rough road",
      "type": "words"
    },
    {
      "text": "F",
      "type": "chords"
    },
    {
      "text": "But it also breeds creation",
      "type": "words"
    },
    {
      "text": "Am",
      "type": "chords"
    },
    {
      "text": "And earthquakes are to a girl’s guitar",
      "type": "words"
    },
    {
      "text": "F",
      "type": "chords"
    },
    {
      "text": "They’re just another good vibration",
      "type": "words"
    },
    {
      "text": "C                    G",
      "type": "chords"
    },
    {
      "text": "And tidal waves couldn’t save the world",
      "type": "words"
    },
    {
      "text": "F        Dm     Am F Am F",
      "type": "chords"
    },
    {
      "text": "From Californication",
      "type": "words"
    },
    {
      "text": "Bridge:",
      "type": "words"
    },
    {
      "text": "Am F Am Am x4",
      "type": "chords"
    },
    {
      "text": "Am",
      "type": "chords"
    },
    {
      "text": "Pay your surgeon very well",
      "type": "words"
    },
    {
      "text": "F",
      "type": "chords"
    },
    {
      "text": "To break the spell of aging",
      "type": "words"
    },
    {
      "text": "Am",
      "type": "chords"
    },
    {
      "text": "Sicker than the rest  There is no test",
      "type": "words"
    },
    {
      "text": "F                         Am",
      "type": "chords"
    },
    {
      "text": "But this is what you’re craving",
      "type": "words"
    },
    {
      "text": "Am            F   Am               F",
      "type": "chords"
    },
    {
      "text": "First born unicorn  Hard core soft porn",
      "type": "words"
    },
    {
      "text": "C           G    Dm    Am  C           G    Dm",
      "type": "chords"
    },
    {
      "text": "Dream of Californication   Dream of Californication x2",
      "type": "words"
    },
    {
      "text": "Bridge:",
      "type": "words"
    },
    {
      "text": "Am F Am Am x4",
      "type": "chords"
    },
    {
      "text": "Ending:",
      "type": "words"
    },
    {
      "text": "Am Am Am F x4",
      "type": "chords"
    }
  ]
}