{
  "songName": "Wonderful Tonight ",
  "lyrics": [
    {
      "text": "Intro : x2",
      "type": "words"
    },
    {
      "text": "G          D/F#             C",
      "type": "chords"
    },
    {
      "text": "D                 G",
      "type": "chords"
    },
    {
      "text": "G               D/F#     C",
      "type": "chords"
    },
    {
      "text": "It's late in the evening",
      "type": "words"
    },
    {
      "text": "C                     D              G",
      "type": "chords"
    },
    {
      "text": "She's wondering what clothes to wear",
      "type": "words"
    },
    {
      "text": "G               D/F#     C",
      "type": "chords"
    },
    {
      "text": "She puts on her make up",
      "type": "words"
    },
    {
      "text": "C               D                 C",
      "type": "chords"
    },
    {
      "text": "And brushes her long blonde hair",
      "type": "words"
    },
    {
      "text": "C            D",
      "type": "chords"
    },
    {
      "text": "And then she asks me",
      "type": "words"
    },
    {
      "text": "G    G/F#   Em",
      "type": "chords"
    },
    {
      "text": "Do I look alright",
      "type": "words"
    },
    {
      "text": "C             D           G     D  C  D",
      "type": "chords"
    },
    {
      "text": "And I say yes, you look wonderful tonight",
      "type": "words"
    },
    {
      "text": "Repeat Intro",
      "type": "words"
    },
    {
      "text": "G          D/F#   C",
      "type": "chords"
    },
    {
      "text": "We go to a party",
      "type": "words"
    },
    {
      "text": "C            D             G",
      "type": "chords"
    },
    {
      "text": "And everyone turns to see",
      "type": "words"
    },
    {
      "text": "G              D/F#  C",
      "type": "chords"
    },
    {
      "text": "This beautiful lady",
      "type": "words"
    },
    {
      "text": "C               D             C",
      "type": "chords"
    },
    {
      "text": "That's walking around with me",
      "type": "words"
    },
    {
      "text": "C            D        G",
      "type": "chords"
    },
    {
      "text": "And then she asks me",
      "type": "words"
    },
    {
      "text": "G      G/F#   Em",
      "type": "chords"
    },
    {
      "text": "Do you feel alright",
      "type": "words"
    },
    {
      "text": "C           D           G",
      "type": "chords"
    },
    {
      "text": "And I say yes, I feel wonderful tonight",
      "type": "words"
    },
    {
      "text": "C",
      "type": "chords"
    },
    {
      "text": "I feel wonderful",
      "type": "words"
    },
    {
      "text": "D               G          G/F#    Em",
      "type": "chords"
    },
    {
      "text": "Because I see the love light in your eyes",
      "type": "words"
    },
    {
      "text": "C            D",
      "type": "chords"
    },
    {
      "text": "And the wonder of it all",
      "type": "words"
    },
    {
      "text": "C             D",
      "type": "chords"
    },
    {
      "text": "Is that you just don't realize",
      "type": "words"
    },
    {
      "text": "G        D  C  D  G  D  C  D",
      "type": "chords"
    },
    {
      "text": "How much I love you",
      "type": "words"
    },
    {
      "text": "Repeat Intro",
      "type": "words"
    },
    {
      "text": "G               D/F#      C",
      "type": "chords"
    },
    {
      "text": "It's time to go home now",
      "type": "words"
    },
    {
      "text": "C                      D     G",
      "type": "chords"
    },
    {
      "text": "And I've got an aching head",
      "type": "words"
    },
    {
      "text": "G                 D/F#     C",
      "type": "chords"
    },
    {
      "text": "So I give her the car keys",
      "type": "words"
    },
    {
      "text": "C               D    C",
      "type": "chords"
    },
    {
      "text": "She helps me to bed",
      "type": "words"
    },
    {
      "text": "C          D         G",
      "type": "chords"
    },
    {
      "text": "And then I tell her",
      "type": "words"
    },
    {
      "text": "G    G/F#         Em",
      "type": "chords"
    },
    {
      "text": "As I turn out the light",
      "type": "words"
    },
    {
      "text": "C",
      "type": "chords"
    },
    {
      "text": "I say my darling",
      "type": "words"
    },
    {
      "text": "D           G     G/F#  Em Em/D",
      "type": "chords"
    },
    {
      "text": "You were wonderful tonight",
      "type": "words"
    },
    {
      "text": "C                 D           G",
      "type": "chords"
    },
    {
      "text": "Oh my darling, you were wonderful tonight",
      "type": "words"
    },
    {
      "text": "Solo:",
      "type": "words"
    },
    {
      "text": "G          D/F#             C",
      "type": "chords"
    },
    {
      "text": "D                   G",
      "type": "chords"
    },
    {
      "text": "G          D/F#             C",
      "type": "chords"
    },
    {
      "text": "Bridge:",
      "type": "words"
    },
    {
      "text": "G C G D x4",
      "type": "chords"
    },
    {
      "text": "D                 G",
      "type": "chords"
    },
    {
      "text": "Bridge:",
      "type": "words"
    },
    {
      "text": "G C G D x4",
      "type": "chords"
    },
    {
      "text": "Ending:",
      "type": "words"
    },
    {
      "text": "G D G C x4",
      "type": "chords"
    }
  ]
}